sunpeek_demo/__init__.py
sunpeek_demo/FHW__array_ArcS__2017-01-01__2017-12-31__1m__UTC.csv
sunpeek_demo/FHW__array_ArcS__2017-05-01__2017-05-02__1m__UTC.csv
sunpeek_demo/FHW__array_ArcS__2017-05-01__2017-05-31__1m__UTC.csv
sunpeek_demo/LICENSE
"sunpeek_demo/Pekasolar, pdf export, density.csv"
"sunpeek_demo/Pekasolar, pdf export, heat capacity.csv"
sunpeek_demo/plant_config_FHW_Arcon_South.json
sunpeek_demo/poetry.lock
sunpeek_demo/pyproject.toml
sunpeek_demo/README.md
sunpeek_demo-0.0.0.dev3.dist-info/LICENSE
sunpeek_demo-0.0.0.dev3.dist-info/METADATA
sunpeek_demo-0.0.0.dev3.dist-info/WHEEL
sunpeek_demo-0.0.0.dev3.dist-info/RECORD
